mcelery/__init__.py
mcelery/celery.py
mcelery/cos.py
mcelery/infer.py
mcelery-0.1.0.dist-info/METADATA
mcelery-0.1.0.dist-info/WHEEL
mcelery-0.1.0.dist-info/top_level.txt
mcelery-0.1.0.dist-info/RECORD
